retryx/__init__.py
retryx-0.2.0.dist-info/LICENSE
retryx-0.2.0.dist-info/METADATA
retryx-0.2.0.dist-info/WHEEL
retryx-0.2.0.dist-info/RECORD
