Metadata-Version: 2.1
Name: retryx
Version: 0.2.0
Summary: 
Author: Your Name
Author-email: you@example.com
Requires-Python: >=3.9,<4.0
Classifier: Programming Language :: Python :: 3
Classifier: Programming Language :: Python :: 3.9
Classifier: Programming Language :: Python :: 3.10
Classifier: Programming Language :: Python :: 3.11
Classifier: Programming Language :: Python :: 3.12
Requires-Dist: bandit (>=1.7.5,<2.0.0)
Requires-Dist: black (>=23.11.0,<24.0.0)
Requires-Dist: coverage (>=7.3.2,<8.0.0)
Requires-Dist: isort (>=5.12.0,<6.0.0)
Requires-Dist: mypy (>=1.7.1,<2.0.0)
Requires-Dist: pytest (>=7.4.3,<8.0.0)
Requires-Dist: pytest-cov (>=4.1.0,<5.0.0)
